flask_http_client/__init__.py
flask_http_client-0.1.6.dist-info/LICENSE
flask_http_client-0.1.6.dist-info/METADATA
flask_http_client-0.1.6.dist-info/WHEEL
flask_http_client-0.1.6.dist-info/RECORD
