Metadata-Version: 2.1
Name: flask-http-client
Version: 0.1.6
Summary: 
License: BSD-3-Clause
Author: codeif
Author-email: me@codeif.com
Requires-Python: >=3.10,<4.0
Classifier: License :: OSI Approved :: BSD License
Classifier: Programming Language :: Python :: 3
Classifier: Programming Language :: Python :: 3.10
Classifier: Programming Language :: Python :: 3.11
Classifier: Programming Language :: Python :: 3.12
Requires-Dist: Flask
Requires-Dist: requests
